chatline/__init__.py
chatline/conversation/__init__.py
chatline/conversation/actions.py
chatline/conversation/history.py
chatline/conversation/messages.py
chatline/conversation/preface.py
chatline/conversation/save_manager.py
chatline/default_messages.py
chatline/display/__init__.py
chatline/display/animations/__init__.py
chatline/display/animations/dot_loader.py
chatline/display/animations/reverse_streamer.py
chatline/display/animations/scroller.py
chatline/display/style/__init__.py
chatline/display/style/definitions.py
chatline/display/style/engine.py
chatline/display/style/strategies.py
chatline/display/terminal.py
chatline/generator.py
chatline/interface.py
chatline/logger.py
chatline/providers/__init__.py
chatline/providers/base.py
chatline/providers/bedrock.py
chatline/providers/openrouter.py
chatline/stream/__init__.py
chatline/stream/embedded.py
chatline/stream/remote.py
chatline-0.4.0.dist-info/METADATA
chatline-0.4.0.dist-info/WHEEL
chatline-0.4.0.dist-info/licenses/LICENSE
chatline-0.4.0.dist-info/RECORD
