Metadata-Version: 2.4
Name: chatline
Version: 0.4.0
Summary: A pretty command line interface for LLM chat.
License: MIT
License-File: LICENSE
Author: Alex Basile
Author-email: basileaw@gmail.com
Requires-Python: >=3.12
Classifier: License :: OSI Approved :: MIT License
Classifier: Programming Language :: Python :: 3
Classifier: Programming Language :: Python :: 3.12
Classifier: Programming Language :: Python :: 3.13
Classifier: Programming Language :: Python :: 3.14
Requires-Dist: aioboto3 (>=13.0.0)
Requires-Dist: boto3
Requires-Dist: httpx
Requires-Dist: prompt-toolkit
Requires-Dist: rich
Requires-Dist: terminaide (>=0.1.6)
